dataUtils/APIErrors.py
dataUtils/DBClient.py
dataUtils/LocalUtils.py
dataUtils/__init__.py
dataUtils/decor.py
rialtic_data_dev_py-1.1.17.dist-info/WHEEL
rialtic_data_dev_py-1.1.17.dist-info/METADATA
rialtic_data_dev_py-1.1.17.dist-info/RECORD
