Metadata-Version: 2.1
Name: rialtic-data-dev-py
Version: 1.1.17
Summary: Data SDK for development purposes at Rialtic.
Home-page: https://rialtic.io
License: Apache-2.0
Keywords: Rialtic,insight,engine,sdk,data
Author: Rialtic
Author-email: engines.data@rialtic.io
Requires-Python: >=3.7,<4.0
Classifier: License :: OSI Approved :: Apache Software License
Classifier: Operating System :: OS Independent
Classifier: Programming Language :: Python :: 3
Classifier: Programming Language :: Python :: 3.10
Classifier: Programming Language :: Python :: 3.7
Classifier: Programming Language :: Python :: 3.8
Classifier: Programming Language :: Python :: 3.9
Requires-Dist: fhir.resources (>=6.1.0,<7.0.0)
Requires-Dist: insight-engine-schema-python (<1.0.0)
Requires-Dist: requests (>=2.26,<3.0)
Project-URL: Repository, https://github.com/rialtic-community/rialtic-data-dev-py
